odoo/addons/mrp_production_grouped_by_product/README.rst
odoo/addons/mrp_production_grouped_by_product/__init__.py
odoo/addons/mrp_production_grouped_by_product/__manifest__.py
odoo/addons/mrp_production_grouped_by_product/i18n/de.po
odoo/addons/mrp_production_grouped_by_product/i18n/es.po
odoo/addons/mrp_production_grouped_by_product/i18n/it.po
odoo/addons/mrp_production_grouped_by_product/i18n/mrp_production_grouped_by_product.pot
odoo/addons/mrp_production_grouped_by_product/models/__init__.py
odoo/addons/mrp_production_grouped_by_product/models/mrp_production.py
odoo/addons/mrp_production_grouped_by_product/models/stock_move.py
odoo/addons/mrp_production_grouped_by_product/models/stock_picking_type.py
odoo/addons/mrp_production_grouped_by_product/models/stock_rule.py
odoo/addons/mrp_production_grouped_by_product/readme/CONFIGURE.rst
odoo/addons/mrp_production_grouped_by_product/readme/CONTRIBUTORS.rst
odoo/addons/mrp_production_grouped_by_product/readme/DESCRIPTION.rst
odoo/addons/mrp_production_grouped_by_product/readme/HISTORY.rst
odoo/addons/mrp_production_grouped_by_product/readme/ROADMAP.rst
odoo/addons/mrp_production_grouped_by_product/static/description/icon.png
odoo/addons/mrp_production_grouped_by_product/static/description/index.html
odoo/addons/mrp_production_grouped_by_product/tests/__init__.py
odoo/addons/mrp_production_grouped_by_product/tests/test_mrp_production_grouped_by_product.py
odoo/addons/mrp_production_grouped_by_product/views/stock_picking_type_views.xml
odoo_addon_mrp_production_grouped_by_product-16.0.1.0.0.3.dist-info/METADATA
odoo_addon_mrp_production_grouped_by_product-16.0.1.0.0.3.dist-info/WHEEL
odoo_addon_mrp_production_grouped_by_product-16.0.1.0.0.3.dist-info/top_level.txt
odoo_addon_mrp_production_grouped_by_product-16.0.1.0.0.3.dist-info/RECORD
